svnlib/__init__.py
svnlib/exceptions.py
svnlib/internals.py
svnlib/svn_error_parser.py
svnlib/svnlib.py
svnlib-0.1.4.1a0.dist-info/METADATA
svnlib-0.1.4.1a0.dist-info/RECORD
svnlib-0.1.4.1a0.dist-info/WHEEL
svnlib-0.1.4.1a0.dist-info/top_level.txt
